<?xml version="1.0" encoding="UTF-8" standalone="no"?>
<galaxy>
    <star blackHole="false" name="Celesta" numGasGiants="0" numPlanets="0" size="1.0" temp="100" x="0" y="0">
        <planet DIMID="0" customIcon="earthlike" dimMapping="" name="Terra">
            <isKnown>true</isKnown>
            <fogColor>1.0,1.0,1.0</fogColor>
            <skyColor>1.0,1.0,1.0</skyColor>
            <gravitationalMultiplier>100</gravitationalMultiplier>
            <orbitalDistance>100</orbitalDistance>
            <orbitalTheta>0</orbitalTheta>
            <orbitalPhi>0</orbitalPhi>
            <avgTemperature>255</avgTemperature>
            <rotationalPeriod>24000</rotationalPeriod>
            <atmosphereDensity>90</atmosphereDensity>
            <generateCraters>false</generateCraters>
            <generateVolcanos>false</generateVolcanos>
            <generateStructures>false</generateStructures>
            <generateGeodes>false</generateGeodes>
            <planet DIMID="145" customIcon="moon" name="Luna">
                <isKnown>true</isKnown>
                <fogColor>1.0,1.0,1.0</fogColor>
                <skyColor>1.0,1.0,1.0</skyColor>
                <gravitationalMultiplier>16</gravitationalMultiplier>
                <orbitalDistance>100</orbitalDistance>
                <orbitalTheta>0</orbitalTheta>
                <orbitalPhi>0</orbitalPhi>
                <avgTemperature>255</avgTemperature>
                <rotationalPeriod>72000</rotationalPeriod>
                <atmosphereDensity>0</atmosphereDensity>
                <generateCraters>false</generateCraters>
                <generateVolcanos>false</generateVolcanos>
                <generateStructures>false</generateStructures>
                <generateGeodes>false</generateGeodes>
                <biomeIds>advancedrocketry:moon,advancedrocketry:moondark</biomeIds>
            </planet>
        </planet>
        <planet DIMID="150" name="Sol-150">
            <isKnown>false</isKnown>
            <GasGiant>true</GasGiant>
            <gas>oxygen</gas>
            <gas>nitrogen</gas>
            <gas>hydrogen</gas>
            <fogColor>1.0,1.0,1.0</fogColor>
            <skyColor>1.0,1.0,1.0</skyColor>
            <gravitationalMultiplier>130</gravitationalMultiplier>
            <orbitalDistance>219</orbitalDistance>
            <orbitalTheta>0</orbitalTheta>
            <orbitalPhi>0</orbitalPhi>
            <avgTemperature>194</avgTemperature>
            <rotationalPeriod>24000</rotationalPeriod>
            <atmosphereDensity>190</atmosphereDensity>
            <generateCraters>false</generateCraters>
            <generateVolcanos>false</generateVolcanos>
            <generateStructures>false</generateStructures>
            <generateGeodes>false</generateGeodes>
            <planet DIMID="151" name="Sol-150: 0">
                <isKnown>false</isKnown>
                <fogColor>1.0,1.0,1.0</fogColor>
                <skyColor>0.8,0.88173735,0.9692825</skyColor>
                <gravitationalMultiplier>50</gravitationalMultiplier>
                <orbitalDistance>172</orbitalDistance>
                <orbitalTheta>177</orbitalTheta>
                <orbitalPhi>-123</orbitalPhi>
                <avgTemperature>195</avgTemperature>
                <rotationalPeriod>192000</rotationalPeriod>
                <atmosphereDensity>29</atmosphereDensity>
                <generateCraters>true</generateCraters>
                <generateVolcanos>false</generateVolcanos>
                <generateStructures>false</generateStructures>
                <generateGeodes>false</generateGeodes>
                <craterFrequencyMultiplier>1.0</craterFrequencyMultiplier>
                <biomeIds>traverse:mountainous_desert,traverse:thicket,traverse:temperate_rainforest,minecraft:mutated_plains,minecraft:mushroom_island</biomeIds>
            </planet>
            <planet DIMID="152" name="Sol-150: 1">
                <isKnown>false</isKnown>
                <fogColor>1.0,1.0,1.0</fogColor>
                <skyColor>0.8,0.96851975,1.0</skyColor>
                <gravitationalMultiplier>68</gravitationalMultiplier>
                <orbitalDistance>188</orbitalDistance>
                <orbitalTheta>81</orbitalTheta>
                <orbitalPhi>-236</orbitalPhi>
                <avgTemperature>186</avgTemperature>
                <rotationalPeriod>76328</rotationalPeriod>
                <atmosphereDensity>28</atmosphereDensity>
                <generateCraters>true</generateCraters>
                <generateVolcanos>false</generateVolcanos>
                <generateStructures>false</generateStructures>
                <generateGeodes>false</generateGeodes>
                <craterFrequencyMultiplier>1.0</craterFrequencyMultiplier>
                <seaLevel>59</seaLevel>
                <biomeIds>advancedrocketry:volcanicbarren,traverse:autumnal_woods,minecraft:birch_forest,traverse:canyon,minecraft:swampland</biomeIds>
            </planet>
            <planet DIMID="153" name="Sol-150: 2">
                <isKnown>false</isKnown>
                <fogColor>1.0,1.0,1.0</fogColor>
                <skyColor>0.8,0.78360635,0.815284</skyColor>
                <gravitationalMultiplier>61</gravitationalMultiplier>
                <orbitalDistance>108</orbitalDistance>
                <orbitalTheta>181</orbitalTheta>
                <orbitalPhi>-63</orbitalPhi>
                <avgTemperature>246</avgTemperature>
                <rotationalPeriod>105735</rotationalPeriod>
                <atmosphereDensity>15</atmosphereDensity>
                <generateCraters>true</generateCraters>
                <generateVolcanos>false</generateVolcanos>
                <generateStructures>false</generateStructures>
                <generateGeodes>false</generateGeodes>
                <craterFrequencyMultiplier>1.0</craterFrequencyMultiplier>
                <biomeIds>advancedrocketry:moon,advancedrocketry:moondark</biomeIds>
            </planet>
        </planet>
        <planet DIMID="154" name="Sol-154">
            <isKnown>false</isKnown>
            <GasGiant>true</GasGiant>
            <gas>oxygen</gas>
            <gas>nitrogen</gas>
            <gas>hydrogen</gas>
            <fogColor>1.0,1.0,1.0</fogColor>
            <skyColor>1.0,1.0,1.0</skyColor>
            <gravitationalMultiplier>123</gravitationalMultiplier>
            <orbitalDistance>209</orbitalDistance>
            <orbitalTheta>0</orbitalTheta>
            <orbitalPhi>0</orbitalPhi>
            <avgTemperature>199</avgTemperature>
            <rotationalPeriod>24000</rotationalPeriod>
            <atmosphereDensity>122</atmosphereDensity>
            <generateCraters>false</generateCraters>
            <generateVolcanos>false</generateVolcanos>
            <generateStructures>false</generateStructures>
            <generateGeodes>false</generateGeodes>
            <planet DIMID="155" name="Sol-154: 0">
                <isKnown>false</isKnown>
                <fogColor>1.0,1.0,1.0</fogColor>
                <skyColor>0.8,0.54197186,0.89976346</skyColor>
                <gravitationalMultiplier>45</gravitationalMultiplier>
                <orbitalDistance>111</orbitalDistance>
                <orbitalTheta>81</orbitalTheta>
                <orbitalPhi>-46</orbitalPhi>
                <avgTemperature>242</avgTemperature>
                <rotationalPeriod>263374</rotationalPeriod>
                <atmosphereDensity>20</atmosphereDensity>
                <generateCraters>true</generateCraters>
                <generateVolcanos>false</generateVolcanos>
                <generateStructures>false</generateStructures>
                <generateGeodes>false</generateGeodes>
                <craterFrequencyMultiplier>1.0</craterFrequencyMultiplier>
                <seaLevel>73</seaLevel>
                <biomeIds>advancedrocketry:moon,advancedrocketry:moondark</biomeIds>
                <oceanBlock>advancedrocketry:oxygenfluid</oceanBlock>
            </planet>
            <planet DIMID="156" name="Sol-154: 1">
                <isKnown>false</isKnown>
                <fogColor>1.0,1.0,1.0</fogColor>
                <skyColor>0.8,0.72154796,1.0</skyColor>
                <gravitationalMultiplier>47</gravitationalMultiplier>
                <orbitalDistance>190</orbitalDistance>
                <orbitalTheta>246</orbitalTheta>
                <orbitalPhi>-239</orbitalPhi>
                <avgTemperature>185</avgTemperature>
                <rotationalPeriod>231162</rotationalPeriod>
                <atmosphereDensity>32</atmosphereDensity>
                <generateCraters>true</generateCraters>
                <generateVolcanos>false</generateVolcanos>
                <generateStructures>false</generateStructures>
                <generateGeodes>false</generateGeodes>
                <craterFrequencyMultiplier>1.0</craterFrequencyMultiplier>
                <biomeIds>minecraft:mutated_mesa_clear_rock,minecraft:forest,advancedrocketry:deepswamp,traverse:autumnal_wooded_hills,minecraft:mutated_birch_forest_hills</biomeIds>
            </planet>
            <planet DIMID="157" name="Sol-154: 2">
                <isKnown>false</isKnown>
                <fogColor>1.0,1.0,1.0</fogColor>
                <skyColor>0.8,0.71515,1.0</skyColor>
                <gravitationalMultiplier>78</gravitationalMultiplier>
                <orbitalDistance>181</orbitalDistance>
                <orbitalTheta>133</orbitalTheta>
                <orbitalPhi>121</orbitalPhi>
                <avgTemperature>190</avgTemperature>
                <rotationalPeriod>50574</rotationalPeriod>
                <atmosphereDensity>34</atmosphereDensity>
                <generateCraters>true</generateCraters>
                <generateVolcanos>false</generateVolcanos>
                <generateStructures>false</generateStructures>
                <generateGeodes>false</generateGeodes>
                <craterFrequencyMultiplier>1.0</craterFrequencyMultiplier>
                <biomeIds>minecraft:mutated_forest,minecraft:mutated_redwood_taiga_hills,minecraft:swampland,minecraft:jungle,traverse:rocky_plateau</biomeIds>
            </planet>
        </planet>
        <planet DIMID="158" name="Sol-158">
            <isKnown>false</isKnown>
            <GasGiant>true</GasGiant>
            <gas>oxygen</gas>
            <gas>nitrogen</gas>
            <gas>hydrogen</gas>
            <fogColor>1.0,1.0,1.0</fogColor>
            <skyColor>1.0,1.0,1.0</skyColor>
            <gravitationalMultiplier>128</gravitationalMultiplier>
            <orbitalDistance>258</orbitalDistance>
            <orbitalTheta>0</orbitalTheta>
            <orbitalPhi>0</orbitalPhi>
            <avgTemperature>179</avgTemperature>
            <rotationalPeriod>24000</rotationalPeriod>
            <atmosphereDensity>128</atmosphereDensity>
            <generateCraters>false</generateCraters>
            <generateVolcanos>false</generateVolcanos>
            <generateStructures>false</generateStructures>
            <generateGeodes>false</generateGeodes>
            <planet DIMID="160" name="Sol-158: 1">
                <isKnown>false</isKnown>
                <fogColor>1.0,1.0,1.0</fogColor>
                <skyColor>0.8,0.63721544,1.0</skyColor>
                <gravitationalMultiplier>61</gravitationalMultiplier>
                <orbitalDistance>169</orbitalDistance>
                <orbitalTheta>201</orbitalTheta>
                <orbitalPhi>144</orbitalPhi>
                <avgTemperature>196</avgTemperature>
                <rotationalPeriod>105735</rotationalPeriod>
                <atmosphereDensity>32</atmosphereDensity>
                <generateCraters>true</generateCraters>
                <generateVolcanos>false</generateVolcanos>
                <generateStructures>false</generateStructures>
                <generateGeodes>false</generateGeodes>
                <craterFrequencyMultiplier>1.0</craterFrequencyMultiplier>
                <biomeIds>minecraft:savanna,minecraft:mutated_redwood_taiga_hills,minecraft:extreme_hills,minecraft:mesa_clear_rock,thaumcraft:eerie</biomeIds>
            </planet>
            <planet DIMID="161" name="Sol-158: 2">
                <isKnown>false</isKnown>
                <fogColor>1.0,1.0,1.0</fogColor>
                <skyColor>0.8,0.81165767,1.0</skyColor>
                <gravitationalMultiplier>83</gravitationalMultiplier>
                <orbitalDistance>171</orbitalDistance>
                <orbitalTheta>76</orbitalTheta>
                <orbitalPhi>80</orbitalPhi>
                <avgTemperature>195</avgTemperature>
                <rotationalPeriod>41973</rotationalPeriod>
                <atmosphereDensity>35</atmosphereDensity>
                <generateCraters>true</generateCraters>
                <generateVolcanos>false</generateVolcanos>
                <generateStructures>false</generateStructures>
                <generateGeodes>false</generateGeodes>
                <craterFrequencyMultiplier>1.0</craterFrequencyMultiplier>
                <biomeIds>minecraft:beaches,minecraft:mutated_forest,minecraft:mutated_redwood_taiga_hills,minecraft:forest,traverse:mini_jungle</biomeIds>
            </planet>
            <planet DIMID="159" name="Sol-158: 0">
                <isKnown>false</isKnown>
                <fogColor>1.0,1.0,1.0</fogColor>
                <skyColor>0.8,0.97732216,0.91044396</skyColor>
                <gravitationalMultiplier>75</gravitationalMultiplier>
                <orbitalDistance>139</orbitalDistance>
                <orbitalTheta>349</orbitalTheta>
                <orbitalPhi>-224</orbitalPhi>
                <avgTemperature>217</avgTemperature>
                <rotationalPeriod>56888</rotationalPeriod>
                <atmosphereDensity>18</atmosphereDensity>
                <generateCraters>true</generateCraters>
                <generateVolcanos>false</generateVolcanos>
                <generateStructures>false</generateStructures>
                <generateGeodes>false</generateGeodes>
                <craterFrequencyMultiplier>1.0</craterFrequencyMultiplier>
                <biomeIds>advancedrocketry:moon,advancedrocketry:moondark</biomeIds>
            </planet>
        </planet>
        <planet DIMID="162" name="Sol-162">
            <isKnown>false</isKnown>
            <GasGiant>true</GasGiant>
            <gas>oxygen</gas>
            <gas>nitrogen</gas>
            <gas>hydrogen</gas>
            <fogColor>1.0,1.0,1.0</fogColor>
            <skyColor>1.0,1.0,1.0</skyColor>
            <gravitationalMultiplier>104</gravitationalMultiplier>
            <orbitalDistance>261</orbitalDistance>
            <orbitalTheta>0</orbitalTheta>
            <orbitalPhi>0</orbitalPhi>
            <avgTemperature>178</avgTemperature>
            <rotationalPeriod>24000</rotationalPeriod>
            <atmosphereDensity>173</atmosphereDensity>
            <generateCraters>false</generateCraters>
            <generateVolcanos>false</generateVolcanos>
            <generateStructures>false</generateStructures>
            <generateGeodes>false</generateGeodes>
            <planet DIMID="163" name="Sol-162: 0">
                <isKnown>false</isKnown>
                <fogColor>1.0,1.0,1.0</fogColor>
                <skyColor>0.8,0.61194336,1.0</skyColor>
                <gravitationalMultiplier>27</gravitationalMultiplier>
                <orbitalDistance>199</orbitalDistance>
                <orbitalTheta>96</orbitalTheta>
                <orbitalPhi>-193</orbitalPhi>
                <avgTemperature>181</avgTemperature>
                <rotationalPeriod>1219326</rotationalPeriod>
                <atmosphereDensity>22</atmosphereDensity>
                <generateCraters>true</generateCraters>
                <generateVolcanos>false</generateVolcanos>
                <generateStructures>false</generateStructures>
                <generateGeodes>false</generateGeodes>
                <craterFrequencyMultiplier>1.0</craterFrequencyMultiplier>
                <seaLevel>43</seaLevel>
                <biomeIds>advancedrocketry:moon,advancedrocketry:moondark</biomeIds>
            </planet>
            <planet DIMID="164" name="Sol-162: 1">
                <isKnown>false</isKnown>
                <fogColor>1.0,1.0,1.0</fogColor>
                <skyColor>0.8,0.9591486,1.0</skyColor>
                <gravitationalMultiplier>52</gravitationalMultiplier>
                <orbitalDistance>158</orbitalDistance>
                <orbitalTheta>118</orbitalTheta>
                <orbitalPhi>-275</orbitalPhi>
                <avgTemperature>203</avgTemperature>
                <rotationalPeriod>161206</rotationalPeriod>
                <atmosphereDensity>20</atmosphereDensity>
                <generateCraters>true</generateCraters>
                <generateVolcanos>false</generateVolcanos>
                <generateStructures>false</generateStructures>
                <generateGeodes>false</generateGeodes>
                <craterFrequencyMultiplier>1.0</craterFrequencyMultiplier>
                <biomeIds>advancedrocketry:moon,advancedrocketry:moondark</biomeIds>
            </planet>
            <planet DIMID="165" name="Sol-162: 2">
                <isKnown>false</isKnown>
                <fogColor>1.0,1.0,1.0</fogColor>
                <skyColor>0.8,0.79340106,0.98493826</skyColor>
                <gravitationalMultiplier>75</gravitationalMultiplier>
                <orbitalDistance>173</orbitalDistance>
                <orbitalTheta>222</orbitalTheta>
                <orbitalPhi>-156</orbitalPhi>
                <avgTemperature>194</avgTemperature>
                <rotationalPeriod>56888</rotationalPeriod>
                <atmosphereDensity>29</atmosphereDensity>
                <generateCraters>true</generateCraters>
                <generateVolcanos>false</generateVolcanos>
                <generateStructures>false</generateStructures>
                <generateGeodes>false</generateGeodes>
                <craterFrequencyMultiplier>1.0</craterFrequencyMultiplier>
                <biomeIds>minecraft:desert,minecraft:mesa,advancedrocketry:volcanicbarren,minecraft:mutated_desert,minecraft:mutated_extreme_hills_with_trees</biomeIds>
            </planet>
        </planet>
        <planet DIMID="100" customIcon="earthlike" dimMapping="" name="Nova">
            <isKnown>true</isKnown>
            <fogColor>1.0,1.0,1.0</fogColor>
            <skyColor>1.0,1.0,1.0</skyColor>
            <gravitationalMultiplier>100</gravitationalMultiplier>
            <orbitalDistance>110</orbitalDistance>
            <orbitalTheta>0</orbitalTheta>
            <orbitalPhi>0</orbitalPhi>
            <avgTemperature>274</avgTemperature>
            <rotationalPeriod>24000</rotationalPeriod>
            <atmosphereDensity>100</atmosphereDensity>
            <generateCraters>false</generateCraters>
            <generateVolcanos>false</generateVolcanos>
            <generateStructures>false</generateStructures>
            <generateGeodes>false</generateGeodes>
        </planet>
        <planet DIMID="166" name="Sol-166">
            <isKnown>false</isKnown>
            <GasGiant>true</GasGiant>
            <gas>oxygen</gas>
            <gas>nitrogen</gas>
            <gas>hydrogen</gas>
            <fogColor>1.0,1.0,1.0</fogColor>
            <skyColor>1.0,1.0,1.0</skyColor>
            <gravitationalMultiplier>130</gravitationalMultiplier>
            <orbitalDistance>235</orbitalDistance>
            <orbitalTheta>0</orbitalTheta>
            <orbitalPhi>0</orbitalPhi>
            <avgTemperature>187</avgTemperature>
            <rotationalPeriod>24000</rotationalPeriod>
            <atmosphereDensity>194</atmosphereDensity>
            <generateCraters>false</generateCraters>
            <generateVolcanos>false</generateVolcanos>
            <generateStructures>false</generateStructures>
            <generateGeodes>false</generateGeodes>
            <planet DIMID="167" name="Sol-166: 0">
                <isKnown>false</isKnown>
                <fogColor>1.0,1.0,1.0</fogColor>
                <skyColor>0.8,0.7082281,0.8376535</skyColor>
                <gravitationalMultiplier>78</gravitationalMultiplier>
                <orbitalDistance>108</orbitalDistance>
                <orbitalTheta>263</orbitalTheta>
                <orbitalPhi>0</orbitalPhi>
                <avgTemperature>246</avgTemperature>
                <rotationalPeriod>50574</rotationalPeriod>
                <atmosphereDensity>24</atmosphereDensity>
                <generateCraters>true</generateCraters>
                <generateVolcanos>false</generateVolcanos>
                <generateStructures>false</generateStructures>
                <generateGeodes>false</generateGeodes>
                <craterFrequencyMultiplier>1.0</craterFrequencyMultiplier>
                <seaLevel>76</seaLevel>
                <biomeIds>advancedrocketry:moon,advancedrocketry:moondark</biomeIds>
                <oceanBlock>advancedrocketry:oxygenfluid</oceanBlock>
            </planet>
            <planet DIMID="168" name="Sol-166: 1">
                <isKnown>false</isKnown>
                <fogColor>1.0,1.0,1.0</fogColor>
                <skyColor>0.8,0.612079,0.9148723</skyColor>
                <gravitationalMultiplier>73</gravitationalMultiplier>
                <orbitalDistance>145</orbitalDistance>
                <orbitalTheta>137</orbitalTheta>
                <orbitalPhi>-135</orbitalPhi>
                <avgTemperature>212</avgTemperature>
                <rotationalPeriod>61693</rotationalPeriod>
                <atmosphereDensity>27</atmosphereDensity>
                <generateCraters>true</generateCraters>
                <generateVolcanos>false</generateVolcanos>
                <generateStructures>false</generateStructures>
                <generateGeodes>false</generateGeodes>
                <craterFrequencyMultiplier>1.0</craterFrequencyMultiplier>
                <biomeIds>minecraft:deep_ocean,minecraft:mutated_savanna,minecraft:mutated_mesa_rock,minecraft:jungle_hills,minecraft:jungle</biomeIds>
            </planet>
        </planet>
        <planet DIMID="169" name="Sol-169">
            <isKnown>false</isKnown>
            <GasGiant>true</GasGiant>
            <gas>oxygen</gas>
            <gas>nitrogen</gas>
            <gas>hydrogen</gas>
            <fogColor>1.0,1.0,1.0</fogColor>
            <skyColor>1.0,1.0,1.0</skyColor>
            <gravitationalMultiplier>130</gravitationalMultiplier>
            <orbitalDistance>186</orbitalDistance>
            <orbitalTheta>0</orbitalTheta>
            <orbitalPhi>0</orbitalPhi>
            <avgTemperature>211</avgTemperature>
            <rotationalPeriod>24000</rotationalPeriod>
            <atmosphereDensity>133</atmosphereDensity>
            <generateCraters>false</generateCraters>
            <generateVolcanos>false</generateVolcanos>
            <generateStructures>false</generateStructures>
            <generateGeodes>false</generateGeodes>
            <planet DIMID="170" name="Sol-169: 0">
                <isKnown>false</isKnown>
                <fogColor>1.0,1.0,1.0</fogColor>
                <skyColor>0.8,0.55731773,1.0</skyColor>
                <gravitationalMultiplier>73</gravitationalMultiplier>
                <orbitalDistance>177</orbitalDistance>
                <orbitalTheta>298</orbitalTheta>
                <orbitalPhi>-130</orbitalPhi>
                <avgTemperature>192</avgTemperature>
                <rotationalPeriod>61693</rotationalPeriod>
                <atmosphereDensity>31</atmosphereDensity>
                <generateCraters>true</generateCraters>
                <generateVolcanos>false</generateVolcanos>
                <generateStructures>false</generateStructures>
                <generateGeodes>false</generateGeodes>
                <craterFrequencyMultiplier>1.0</craterFrequencyMultiplier>
                <seaLevel>72</seaLevel>
                <biomeIds>minecraft:mutated_roofed_forest,minecraft:mutated_forest,minecraft:mutated_redwood_taiga,minecraft:swampland,minecraft:birch_forest_hills</biomeIds>
            </planet>
            <planet DIMID="171" name="Sol-169: 1">
                <isKnown>false</isKnown>
                <fogColor>1.0,1.0,1.0</fogColor>
                <skyColor>0.8,0.8056158,0.9657668</skyColor>
                <gravitationalMultiplier>81</gravitationalMultiplier>
                <orbitalDistance>171</orbitalDistance>
                <orbitalTheta>231</orbitalTheta>
                <orbitalPhi>-81</orbitalPhi>
                <avgTemperature>195</avgTemperature>
                <rotationalPeriod>45160</rotationalPeriod>
                <atmosphereDensity>31</atmosphereDensity>
                <generateCraters>true</generateCraters>
                <generateVolcanos>false</generateVolcanos>
                <generateStructures>false</generateStructures>
                <generateGeodes>false</generateGeodes>
                <craterFrequencyMultiplier>1.0</craterFrequencyMultiplier>
                <biomeIds>minecraft:mushroom_island,minecraft:jungle,minecraft:mesa_clear_rock,minecraft:mutated_forest,advancedrocketry:oceanspires</biomeIds>
            </planet>
            <planet DIMID="172" name="Sol-169: 2">
                <isKnown>false</isKnown>
                <fogColor>1.0,1.0,1.0</fogColor>
                <skyColor>0.8,0.6395528,0.7702347</skyColor>
                <gravitationalMultiplier>45</gravitationalMultiplier>
                <orbitalDistance>104</orbitalDistance>
                <orbitalTheta>323</orbitalTheta>
                <orbitalPhi>-191</orbitalPhi>
                <avgTemperature>250</avgTemperature>
                <rotationalPeriod>263374</rotationalPeriod>
                <atmosphereDensity>14</atmosphereDensity>
                <generateCraters>true</generateCraters>
                <generateVolcanos>false</generateVolcanos>
                <generateStructures>false</generateStructures>
                <generateGeodes>false</generateGeodes>
                <craterFrequencyMultiplier>1.0</craterFrequencyMultiplier>
                <biomeIds>advancedrocketry:moon,advancedrocketry:moondark</biomeIds>
            </planet>
            <planet DIMID="173" name="Sol-169: 3">
                <isKnown>false</isKnown>
                <fogColor>1.0,1.0,1.0</fogColor>
                <skyColor>0.8,0.6786908,0.94840074</skyColor>
                <gravitationalMultiplier>88</gravitationalMultiplier>
                <orbitalDistance>152</orbitalDistance>
                <orbitalTheta>347</orbitalTheta>
                <orbitalPhi>-59</orbitalPhi>
                <avgTemperature>207</avgTemperature>
                <rotationalPeriod>35217</rotationalPeriod>
                <atmosphereDensity>15</atmosphereDensity>
                <generateCraters>true</generateCraters>
                <generateVolcanos>false</generateVolcanos>
                <generateStructures>false</generateStructures>
                <generateGeodes>false</generateGeodes>
                <craterFrequencyMultiplier>1.0</craterFrequencyMultiplier>
                <biomeIds>advancedrocketry:moon,advancedrocketry:moondark</biomeIds>
            </planet>
            <planet DIMID="174" name="Sol-169: 4">
                <isKnown>false</isKnown>
                <fogColor>1.0,1.0,1.0</fogColor>
                <skyColor>0.8,0.5401212,1.0</skyColor>
                <gravitationalMultiplier>73</gravitationalMultiplier>
                <orbitalDistance>175</orbitalDistance>
                <orbitalTheta>256</orbitalTheta>
                <orbitalPhi>251</orbitalPhi>
                <avgTemperature>193</avgTemperature>
                <rotationalPeriod>61693</rotationalPeriod>
                <atmosphereDensity>37</atmosphereDensity>
                <generateCraters>true</generateCraters>
                <generateVolcanos>false</generateVolcanos>
                <generateStructures>false</generateStructures>
                <generateGeodes>false</generateGeodes>
                <craterFrequencyMultiplier>1.0</craterFrequencyMultiplier>
                <biomeIds>minecraft:mutated_birch_forest_hills,traverse:meadow,minecraft:mutated_redwood_taiga,advancedrocketry:oceanspires,minecraft:ocean</biomeIds>
            </planet>
        </planet>
    </star>
    <star blackHole="false" name="Stellaria" numGasGiants="0" numPlanets="0" size="1.0" temp="105" x="5" y="7">
        <planet DIMID="146" name="Euclydes Prime">
            <isKnown>true</isKnown>
            <hasRings>true</hasRings>
            <ringColor>0.4,0.4,0.7</ringColor>
            <fogColor>1.0,1.0,1.0</fogColor>
            <skyColor>1.0,1.0,1.0</skyColor>
            <gravitationalMultiplier>104</gravitationalMultiplier>
            <orbitalDistance>90</orbitalDistance>
            <orbitalTheta>0</orbitalTheta>
            <orbitalPhi>0</orbitalPhi>
            <avgTemperature>318</avgTemperature>
            <rotationalPeriod>28000</rotationalPeriod>
            <atmosphereDensity>110</atmosphereDensity>
            <generateCraters>false</generateCraters>
            <generateVolcanos>false</generateVolcanos>
            <generateStructures>false</generateStructures>
            <generateGeodes>false</generateGeodes>
            <biomeIds>advancedrocketry:alien forest,advancedrocketry:oceanspires,minecraft:ocean</biomeIds>
            <oceanBlock>gregtech:fluid.blue_vitriol_water_solution</oceanBlock>
        </planet>
        <planet DIMID="179" name="Sol-179">
            <isKnown>false</isKnown>
            <GasGiant>true</GasGiant>
            <gas>oxygen</gas>
            <gas>nitrogen</gas>
            <gas>hydrogen</gas>
            <fogColor>1.0,1.0,1.0</fogColor>
            <skyColor>1.0,1.0,1.0</skyColor>
            <gravitationalMultiplier>98</gravitationalMultiplier>
            <orbitalDistance>263</orbitalDistance>
            <orbitalTheta>0</orbitalTheta>
            <orbitalPhi>0</orbitalPhi>
            <avgTemperature>186</avgTemperature>
            <rotationalPeriod>24000</rotationalPeriod>
            <atmosphereDensity>146</atmosphereDensity>
            <generateCraters>false</generateCraters>
            <generateVolcanos>false</generateVolcanos>
            <generateStructures>false</generateStructures>
            <generateGeodes>false</generateGeodes>
        </planet>
        <planet DIMID="180" name="Sol-180">
            <isKnown>false</isKnown>
            <GasGiant>true</GasGiant>
            <gas>oxygen</gas>
            <gas>nitrogen</gas>
            <gas>hydrogen</gas>
            <fogColor>1.0,1.0,1.0</fogColor>
            <skyColor>1.0,1.0,1.0</skyColor>
            <gravitationalMultiplier>92</gravitationalMultiplier>
            <orbitalDistance>259</orbitalDistance>
            <orbitalTheta>0</orbitalTheta>
            <orbitalPhi>0</orbitalPhi>
            <avgTemperature>187</avgTemperature>
            <rotationalPeriod>24000</rotationalPeriod>
            <atmosphereDensity>115</atmosphereDensity>
            <generateCraters>false</generateCraters>
            <generateVolcanos>false</generateVolcanos>
            <generateStructures>false</generateStructures>
            <generateGeodes>false</generateGeodes>
        </planet>
        <planet DIMID="181" name="Sol-181">
            <isKnown>false</isKnown>
            <GasGiant>true</GasGiant>
            <gas>oxygen</gas>
            <gas>nitrogen</gas>
            <gas>hydrogen</gas>
            <fogColor>1.0,1.0,1.0</fogColor>
            <skyColor>1.0,1.0,1.0</skyColor>
            <gravitationalMultiplier>130</gravitationalMultiplier>
            <orbitalDistance>217</orbitalDistance>
            <orbitalTheta>0</orbitalTheta>
            <orbitalPhi>0</orbitalPhi>
            <avgTemperature>205</avgTemperature>
            <rotationalPeriod>24000</rotationalPeriod>
            <atmosphereDensity>122</atmosphereDensity>
            <generateCraters>false</generateCraters>
            <generateVolcanos>false</generateVolcanos>
            <generateStructures>false</generateStructures>
            <generateGeodes>false</generateGeodes>
            <planet DIMID="182" name="Sol-181: 0">
                <isKnown>false</isKnown>
                <fogColor>1.0,1.0,1.0</fogColor>
                <skyColor>0.8,0.848209,0.9419382</skyColor>
                <gravitationalMultiplier>58</gravitationalMultiplier>
                <orbitalDistance>143</orbitalDistance>
                <orbitalTheta>33</orbitalTheta>
                <orbitalPhi>2</orbitalPhi>
                <avgTemperature>224</avgTemperature>
                <rotationalPeriod>123006</rotationalPeriod>
                <atmosphereDensity>19</atmosphereDensity>
                <generateCraters>true</generateCraters>
                <generateVolcanos>false</generateVolcanos>
                <generateStructures>false</generateStructures>
                <generateGeodes>false</generateGeodes>
                <craterFrequencyMultiplier>1.0</craterFrequencyMultiplier>
                <seaLevel>76</seaLevel>
                <biomeIds>advancedrocketry:moon,advancedrocketry:moondark</biomeIds>
                <oceanBlock>advancedrocketry:oxygenfluid</oceanBlock>
            </planet>
        </planet>
        <planet DIMID="185" name="Sol-185">
            <isKnown>false</isKnown>
            <GasGiant>true</GasGiant>
            <gas>oxygen</gas>
            <gas>hydrogen</gas>
            <gas>nitrogen</gas>
            <fogColor>1.0,1.0,1.0</fogColor>
            <skyColor>1.0,1.0,1.0</skyColor>
            <gravitationalMultiplier>100</gravitationalMultiplier>
            <orbitalDistance>273</orbitalDistance>
            <orbitalTheta>0</orbitalTheta>
            <orbitalPhi>0</orbitalPhi>
            <avgTemperature>182</avgTemperature>
            <rotationalPeriod>24000</rotationalPeriod>
            <atmosphereDensity>172</atmosphereDensity>
            <generateCraters>false</generateCraters>
            <generateVolcanos>false</generateVolcanos>
            <generateStructures>false</generateStructures>
            <generateGeodes>false</generateGeodes>
            <planet DIMID="186" name="Sol-183: 2">
                <isKnown>false</isKnown>
                <fogColor>1.0,1.0,1.0</fogColor>
                <skyColor>0.8,0.9683665,0.0</skyColor>
                <gravitationalMultiplier>75</gravitationalMultiplier>
                <orbitalDistance>138</orbitalDistance>
                <orbitalTheta>340</orbitalTheta>
                <orbitalPhi>-52</orbitalPhi>
                <avgTemperature>516</avgTemperature>
                <rotationalPeriod>56888</rotationalPeriod>
                <atmosphereDensity>14</atmosphereDensity>
                <generateCraters>true</generateCraters>
                <generateVolcanos>true</generateVolcanos>
                <generateStructures>false</generateStructures>
                <generateGeodes>false</generateGeodes>
                <craterFrequencyMultiplier>1.0</craterFrequencyMultiplier>
                <volcanoFrequencyMultiplier>1.0</volcanoFrequencyMultiplier>
                <biomeIds>advancedrocketry:moon,advancedrocketry:moondark</biomeIds>
                <oceanBlock>minecraft:lava</oceanBlock>
            </planet>
            <planet DIMID="187" name="Sol-187">
                <isKnown>false</isKnown>
                <GasGiant>true</GasGiant>
                <gas>oxygen</gas>
                <gas>nitrogen</gas>
                <gas>hydrogen</gas>
                <fogColor>1.0,1.0,1.0</fogColor>
                <skyColor>1.0,1.0,1.0</skyColor>
                <gravitationalMultiplier>130</gravitationalMultiplier>
                <orbitalDistance>239</orbitalDistance>
                <orbitalTheta>0</orbitalTheta>
                <orbitalPhi>0</orbitalPhi>
                <avgTemperature>441</avgTemperature>
                <rotationalPeriod>24000</rotationalPeriod>
                <atmosphereDensity>112</atmosphereDensity>
                <generateCraters>false</generateCraters>
                <generateVolcanos>false</generateVolcanos>
                <generateStructures>false</generateStructures>
                <generateGeodes>false</generateGeodes>
                <planet DIMID="192" name="Sol-187: 4">
                    <isKnown>false</isKnown>
                    <fogColor>1.0,1.0,1.0</fogColor>
                    <skyColor>0.8,0.5382596,0.0</skyColor>
                    <gravitationalMultiplier>77</gravitationalMultiplier>
                    <orbitalDistance>133</orbitalDistance>
                    <orbitalTheta>353</orbitalTheta>
                    <orbitalPhi>25</orbitalPhi>
                    <avgTemperature>526</avgTemperature>
                    <rotationalPeriod>52570</rotationalPeriod>
                    <atmosphereDensity>25</atmosphereDensity>
                    <generateCraters>true</generateCraters>
                    <generateVolcanos>true</generateVolcanos>
                    <generateStructures>false</generateStructures>
                    <generateGeodes>false</generateGeodes>
                    <craterFrequencyMultiplier>1.0</craterFrequencyMultiplier>
                    <volcanoFrequencyMultiplier>1.0</volcanoFrequencyMultiplier>
                    <biomeIds>advancedrocketry:moon,advancedrocketry:moondark</biomeIds>
                    <oceanBlock>minecraft:lava</oceanBlock>
                </planet>
                <planet DIMID="188" name="Sol-187: 0">
                    <isKnown>false</isKnown>
                    <fogColor>1.0,1.0,1.0</fogColor>
                    <skyColor>0.8,0.9845816,0.0</skyColor>
                    <gravitationalMultiplier>49</gravitationalMultiplier>
                    <orbitalDistance>131</orbitalDistance>
                    <orbitalTheta>206</orbitalTheta>
                    <orbitalPhi>-174</orbitalPhi>
                    <avgTemperature>530</avgTemperature>
                    <rotationalPeriod>203996</rotationalPeriod>
                    <atmosphereDensity>17</atmosphereDensity>
                    <generateCraters>true</generateCraters>
                    <generateVolcanos>true</generateVolcanos>
                    <generateStructures>false</generateStructures>
                    <generateGeodes>false</generateGeodes>
                    <craterFrequencyMultiplier>1.0</craterFrequencyMultiplier>
                    <volcanoFrequencyMultiplier>1.0</volcanoFrequencyMultiplier>
                    <seaLevel>72</seaLevel>
                    <biomeIds>advancedrocketry:moon,advancedrocketry:moondark</biomeIds>
                    <oceanBlock>minecraft:lava</oceanBlock>
                </planet>
                <planet DIMID="189" name="Sol-187: 1">
                    <isKnown>false</isKnown>
                    <fogColor>1.0,1.0,1.0</fogColor>
                    <skyColor>0.8,0.50748396,0.25215685</skyColor>
                    <gravitationalMultiplier>76</gravitationalMultiplier>
                    <orbitalDistance>202</orbitalDistance>
                    <orbitalTheta>180</orbitalTheta>
                    <orbitalPhi>-217</orbitalPhi>
                    <avgTemperature>426</avgTemperature>
                    <rotationalPeriod>54672</rotationalPeriod>
                    <atmosphereDensity>32</atmosphereDensity>
                    <generateCraters>true</generateCraters>
                    <generateVolcanos>false</generateVolcanos>
                    <generateStructures>false</generateStructures>
                    <generateGeodes>false</generateGeodes>
                    <craterFrequencyMultiplier>1.0</craterFrequencyMultiplier>
                    <biomeIds>advancedrocketry:stormland,minecraft:mutated_savanna,traverse:mountainous_desert,minecraft:savanna_rock,minecraft:frozen_ocean</biomeIds>
                </planet>
                <planet DIMID="190" name="Sol-187: 2">
                    <isKnown>false</isKnown>
                    <fogColor>1.0,1.0,1.0</fogColor>
                    <skyColor>0.8,0.6796143,0.0</skyColor>
                    <gravitationalMultiplier>61</gravitationalMultiplier>
                    <orbitalDistance>143</orbitalDistance>
                    <orbitalTheta>39</orbitalTheta>
                    <orbitalPhi>35</orbitalPhi>
                    <avgTemperature>507</avgTemperature>
                    <rotationalPeriod>105735</rotationalPeriod>
                    <atmosphereDensity>14</atmosphereDensity>
                    <generateCraters>true</generateCraters>
                    <generateVolcanos>true</generateVolcanos>
                    <generateStructures>false</generateStructures>
                    <generateGeodes>false</generateGeodes>
                    <craterFrequencyMultiplier>1.0</craterFrequencyMultiplier>
                    <volcanoFrequencyMultiplier>1.0</volcanoFrequencyMultiplier>
                    <seaLevel>72</seaLevel>
                    <biomeIds>advancedrocketry:moon,advancedrocketry:moondark</biomeIds>
                    <oceanBlock>minecraft:lava</oceanBlock>
                </planet>
                <planet DIMID="191" name="Sol-187: 3">
                    <isKnown>false</isKnown>
                    <fogColor>1.0,1.0,1.0</fogColor>
                    <skyColor>0.8,0.8416947,0.080251634</skyColor>
                    <gravitationalMultiplier>78</gravitationalMultiplier>
                    <orbitalDistance>170</orbitalDistance>
                    <orbitalTheta>325</orbitalTheta>
                    <orbitalPhi>-85</orbitalPhi>
                    <avgTemperature>465</avgTemperature>
                    <rotationalPeriod>50574</rotationalPeriod>
                    <atmosphereDensity>17</atmosphereDensity>
                    <generateCraters>true</generateCraters>
                    <generateVolcanos>true</generateVolcanos>
                    <generateStructures>false</generateStructures>
                    <generateGeodes>false</generateGeodes>
                    <craterFrequencyMultiplier>1.0</craterFrequencyMultiplier>
                    <volcanoFrequencyMultiplier>1.0</volcanoFrequencyMultiplier>
                    <biomeIds>advancedrocketry:moon,advancedrocketry:moondark</biomeIds>
                    <oceanBlock>minecraft:lava</oceanBlock>
                </planet>
            </planet>
            <planet DIMID="188" name="Sol-187: 0">
                <isKnown>false</isKnown>
                <fogColor>1.0,1.0,1.0</fogColor>
                <skyColor>0.8,0.9845816,0.0</skyColor>
                <gravitationalMultiplier>49</gravitationalMultiplier>
                <orbitalDistance>131</orbitalDistance>
                <orbitalTheta>206</orbitalTheta>
                <orbitalPhi>-174</orbitalPhi>
                <avgTemperature>530</avgTemperature>
                <rotationalPeriod>203996</rotationalPeriod>
                <atmosphereDensity>17</atmosphereDensity>
                <generateCraters>true</generateCraters>
                <generateVolcanos>true</generateVolcanos>
                <generateStructures>false</generateStructures>
                <generateGeodes>false</generateGeodes>
                <craterFrequencyMultiplier>1.0</craterFrequencyMultiplier>
                <volcanoFrequencyMultiplier>1.0</volcanoFrequencyMultiplier>
                <seaLevel>72</seaLevel>
                <biomeIds>advancedrocketry:moon,advancedrocketry:moondark</biomeIds>
                <oceanBlock>minecraft:lava</oceanBlock>
            </planet>
            <planet DIMID="189" name="Sol-187: 1">
                <isKnown>false</isKnown>
                <fogColor>1.0,1.0,1.0</fogColor>
                <skyColor>0.8,0.50748396,0.25215685</skyColor>
                <gravitationalMultiplier>76</gravitationalMultiplier>
                <orbitalDistance>202</orbitalDistance>
                <orbitalTheta>180</orbitalTheta>
                <orbitalPhi>-217</orbitalPhi>
                <avgTemperature>426</avgTemperature>
                <rotationalPeriod>54672</rotationalPeriod>
                <atmosphereDensity>32</atmosphereDensity>
                <generateCraters>true</generateCraters>
                <generateVolcanos>false</generateVolcanos>
                <generateStructures>false</generateStructures>
                <generateGeodes>false</generateGeodes>
                <craterFrequencyMultiplier>1.0</craterFrequencyMultiplier>
                <biomeIds>advancedrocketry:stormland,minecraft:mutated_savanna,traverse:mountainous_desert,minecraft:savanna_rock,minecraft:frozen_ocean</biomeIds>
            </planet>
            <planet DIMID="190" name="Sol-187: 2">
                <isKnown>false</isKnown>
                <fogColor>1.0,1.0,1.0</fogColor>
                <skyColor>0.8,0.6796143,0.0</skyColor>
                <gravitationalMultiplier>61</gravitationalMultiplier>
                <orbitalDistance>143</orbitalDistance>
                <orbitalTheta>39</orbitalTheta>
                <orbitalPhi>35</orbitalPhi>
                <avgTemperature>507</avgTemperature>
                <rotationalPeriod>105735</rotationalPeriod>
                <atmosphereDensity>14</atmosphereDensity>
                <generateCraters>true</generateCraters>
                <generateVolcanos>true</generateVolcanos>
                <generateStructures>false</generateStructures>
                <generateGeodes>false</generateGeodes>
                <craterFrequencyMultiplier>1.0</craterFrequencyMultiplier>
                <volcanoFrequencyMultiplier>1.0</volcanoFrequencyMultiplier>
                <seaLevel>72</seaLevel>
                <biomeIds>advancedrocketry:moon,advancedrocketry:moondark</biomeIds>
                <oceanBlock>minecraft:lava</oceanBlock>
            </planet>
            <planet DIMID="191" name="Sol-187: 3">
                <isKnown>false</isKnown>
                <fogColor>1.0,1.0,1.0</fogColor>
                <skyColor>0.8,0.8416947,0.080251634</skyColor>
                <gravitationalMultiplier>78</gravitationalMultiplier>
                <orbitalDistance>170</orbitalDistance>
                <orbitalTheta>325</orbitalTheta>
                <orbitalPhi>-85</orbitalPhi>
                <avgTemperature>465</avgTemperature>
                <rotationalPeriod>50574</rotationalPeriod>
                <atmosphereDensity>17</atmosphereDensity>
                <generateCraters>true</generateCraters>
                <generateVolcanos>true</generateVolcanos>
                <generateStructures>false</generateStructures>
                <generateGeodes>false</generateGeodes>
                <craterFrequencyMultiplier>1.0</craterFrequencyMultiplier>
                <volcanoFrequencyMultiplier>1.0</volcanoFrequencyMultiplier>
                <biomeIds>advancedrocketry:moon,advancedrocketry:moondark</biomeIds>
                <oceanBlock>minecraft:lava</oceanBlock>
            </planet>
        </planet>
        <planet DIMID="171" name="Sol-171">
            <isKnown>false</isKnown>
            <GasGiant>true</GasGiant>
            <gas>oxygen</gas>
            <gas>hydrogen</gas>
            <gas>nitrogen</gas>
            <fogColor>1.0,1.0,1.0</fogColor>
            <skyColor>1.0,1.0,1.0</skyColor>
            <gravitationalMultiplier>130</gravitationalMultiplier>
            <orbitalDistance>228</orbitalDistance>
            <orbitalTheta>0</orbitalTheta>
            <orbitalPhi>0</orbitalPhi>
            <avgTemperature>200</avgTemperature>
            <rotationalPeriod>24000</rotationalPeriod>
            <atmosphereDensity>183</atmosphereDensity>
            <generateCraters>false</generateCraters>
            <generateVolcanos>false</generateVolcanos>
            <generateStructures>false</generateStructures>
            <generateGeodes>false</generateGeodes>
            <planet DIMID="172" name="Sol-169: 2">
                <isKnown>false</isKnown>
                <fogColor>1.0,1.0,1.0</fogColor>
                <skyColor>0.8,0.6395528,0.7702347</skyColor>
                <gravitationalMultiplier>45</gravitationalMultiplier>
                <orbitalDistance>104</orbitalDistance>
                <orbitalTheta>323</orbitalTheta>
                <orbitalPhi>-191</orbitalPhi>
                <avgTemperature>250</avgTemperature>
                <rotationalPeriod>263374</rotationalPeriod>
                <atmosphereDensity>14</atmosphereDensity>
                <generateCraters>true</generateCraters>
                <generateVolcanos>false</generateVolcanos>
                <generateStructures>false</generateStructures>
                <generateGeodes>false</generateGeodes>
                <craterFrequencyMultiplier>1.0</craterFrequencyMultiplier>
                <biomeIds>advancedrocketry:moon,advancedrocketry:moondark</biomeIds>
            </planet>
        </planet>
        <planet DIMID="173" name="Sol-173">
            <isKnown>false</isKnown>
            <GasGiant>true</GasGiant>
            <gas>oxygen</gas>
            <gas>hydrogen</gas>
            <gas>nitrogen</gas>
            <fogColor>1.0,1.0,1.0</fogColor>
            <skyColor>1.0,1.0,1.0</skyColor>
            <gravitationalMultiplier>130</gravitationalMultiplier>
            <orbitalDistance>251</orbitalDistance>
            <orbitalTheta>0</orbitalTheta>
            <orbitalPhi>0</orbitalPhi>
            <avgTemperature>190</avgTemperature>
            <rotationalPeriod>24000</rotationalPeriod>
            <atmosphereDensity>183</atmosphereDensity>
            <generateCraters>false</generateCraters>
            <generateVolcanos>false</generateVolcanos>
            <generateStructures>false</generateStructures>
            <generateGeodes>false</generateGeodes>
            <planet DIMID="176" name="Sol-175: 0">
                <isKnown>false</isKnown>
                <fogColor>1.0,1.0,1.0</fogColor>
                <skyColor>0.8,0.83858865,0.9017167</skyColor>
                <gravitationalMultiplier>85</gravitationalMultiplier>
                <orbitalDistance>142</orbitalDistance>
                <orbitalTheta>66</orbitalTheta>
                <orbitalPhi>76</orbitalPhi>
                <avgTemperature>225</avgTemperature>
                <rotationalPeriod>39079</rotationalPeriod>
                <atmosphereDensity>14</atmosphereDensity>
                <generateCraters>true</generateCraters>
                <generateVolcanos>false</generateVolcanos>
                <generateStructures>false</generateStructures>
                <generateGeodes>false</generateGeodes>
                <craterFrequencyMultiplier>1.0</craterFrequencyMultiplier>
                <biomeIds>advancedrocketry:moon,advancedrocketry:moondark</biomeIds>
            </planet>
            <planet DIMID="174" name="Sol-169: 4">
                <isKnown>false</isKnown>
                <fogColor>1.0,1.0,1.0</fogColor>
                <skyColor>0.8,0.5401212,1.0</skyColor>
                <gravitationalMultiplier>73</gravitationalMultiplier>
                <orbitalDistance>175</orbitalDistance>
                <orbitalTheta>256</orbitalTheta>
                <orbitalPhi>251</orbitalPhi>
                <avgTemperature>193</avgTemperature>
                <rotationalPeriod>61693</rotationalPeriod>
                <atmosphereDensity>37</atmosphereDensity>
                <generateCraters>true</generateCraters>
                <generateVolcanos>false</generateVolcanos>
                <generateStructures>false</generateStructures>
                <generateGeodes>false</generateGeodes>
                <craterFrequencyMultiplier>1.0</craterFrequencyMultiplier>
                <biomeIds>minecraft:mutated_birch_forest_hills,traverse:meadow,minecraft:mutated_redwood_taiga,advancedrocketry:oceanspires,minecraft:ocean</biomeIds>
            </planet>
            <planet DIMID="175" name="Sol-175">
                <isKnown>false</isKnown>
                <GasGiant>true</GasGiant>
                <gas>oxygen</gas>
                <gas>nitrogen</gas>
                <gas>hydrogen</gas>
                <fogColor>1.0,1.0,1.0</fogColor>
                <skyColor>1.0,1.0,1.0</skyColor>
                <gravitationalMultiplier>130</gravitationalMultiplier>
                <orbitalDistance>250</orbitalDistance>
                <orbitalTheta>0</orbitalTheta>
                <orbitalPhi>0</orbitalPhi>
                <avgTemperature>191</avgTemperature>
                <rotationalPeriod>24000</rotationalPeriod>
                <atmosphereDensity>126</atmosphereDensity>
                <generateCraters>false</generateCraters>
                <generateVolcanos>false</generateVolcanos>
                <generateStructures>false</generateStructures>
                <generateGeodes>false</generateGeodes>
                <planet DIMID="176" name="Sol-175: 0">
                    <isKnown>false</isKnown>
                    <fogColor>1.0,1.0,1.0</fogColor>
                    <skyColor>0.8,0.83858865,0.9017167</skyColor>
                    <gravitationalMultiplier>85</gravitationalMultiplier>
                    <orbitalDistance>142</orbitalDistance>
                    <orbitalTheta>66</orbitalTheta>
                    <orbitalPhi>76</orbitalPhi>
                    <avgTemperature>225</avgTemperature>
                    <rotationalPeriod>39079</rotationalPeriod>
                    <atmosphereDensity>14</atmosphereDensity>
                    <generateCraters>true</generateCraters>
                    <generateVolcanos>false</generateVolcanos>
                    <generateStructures>false</generateStructures>
                    <generateGeodes>false</generateGeodes>
                    <craterFrequencyMultiplier>1.0</craterFrequencyMultiplier>
                    <biomeIds>advancedrocketry:moon,advancedrocketry:moondark</biomeIds>
                </planet>
                <planet DIMID="177" name="Sol-175: 1">
                    <isKnown>false</isKnown>
                    <fogColor>1.0,1.0,1.0</fogColor>
                    <skyColor>0.8,0.7194652,1.0</skyColor>
                    <gravitationalMultiplier>47</gravitationalMultiplier>
                    <orbitalDistance>190</orbitalDistance>
                    <orbitalTheta>81</orbitalTheta>
                    <orbitalPhi>-334</orbitalPhi>
                    <avgTemperature>194</avgTemperature>
                    <rotationalPeriod>231162</rotationalPeriod>
                    <atmosphereDensity>27</atmosphereDensity>
                    <generateCraters>true</generateCraters>
                    <generateVolcanos>false</generateVolcanos>
                    <generateStructures>false</generateStructures>
                    <generateGeodes>false</generateGeodes>
                    <craterFrequencyMultiplier>1.0</craterFrequencyMultiplier>
                    <biomeIds>minecraft:mushroom_island_shore,traverse:green_swamp,minecraft:mutated_mesa_clear_rock,minecraft:savanna,minecraft:forest</biomeIds>
                </planet>
                <planet DIMID="178" name="Sol-175: 2">
                    <isKnown>false</isKnown>
                    <fogColor>1.0,1.0,1.0</fogColor>
                    <skyColor>0.8,0.8275626,0.9647331</skyColor>
                    <gravitationalMultiplier>67</gravitationalMultiplier>
                    <orbitalDistance>167</orbitalDistance>
                    <orbitalTheta>348</orbitalTheta>
                    <orbitalPhi>-262</orbitalPhi>
                    <avgTemperature>207</avgTemperature>
                    <rotationalPeriod>79797</rotationalPeriod>
                    <atmosphereDensity>14</atmosphereDensity>
                    <generateCraters>true</generateCraters>
                    <generateVolcanos>false</generateVolcanos>
                    <generateStructures>false</generateStructures>
                    <generateGeodes>false</generateGeodes>
                    <craterFrequencyMultiplier>1.0</craterFrequencyMultiplier>
                    <biomeIds>advancedrocketry:moon,advancedrocketry:moondark</biomeIds>
                </planet>
            </planet>
        </planet>
        <planet DIMID="175" name="Sol-175">
            <isKnown>false</isKnown>
            <GasGiant>true</GasGiant>
            <gas>oxygen</gas>
            <gas>nitrogen</gas>
            <gas>hydrogen</gas>
            <fogColor>1.0,1.0,1.0</fogColor>
            <skyColor>1.0,1.0,1.0</skyColor>
            <gravitationalMultiplier>130</gravitationalMultiplier>
            <orbitalDistance>250</orbitalDistance>
            <orbitalTheta>0</orbitalTheta>
            <orbitalPhi>0</orbitalPhi>
            <avgTemperature>191</avgTemperature>
            <rotationalPeriod>24000</rotationalPeriod>
            <atmosphereDensity>126</atmosphereDensity>
            <generateCraters>false</generateCraters>
            <generateVolcanos>false</generateVolcanos>
            <generateStructures>false</generateStructures>
            <generateGeodes>false</generateGeodes>
            <planet DIMID="176" name="Sol-175: 0">
                <isKnown>false</isKnown>
                <fogColor>1.0,1.0,1.0</fogColor>
                <skyColor>0.8,0.83858865,0.9017167</skyColor>
                <gravitationalMultiplier>85</gravitationalMultiplier>
                <orbitalDistance>142</orbitalDistance>
                <orbitalTheta>66</orbitalTheta>
                <orbitalPhi>76</orbitalPhi>
                <avgTemperature>225</avgTemperature>
                <rotationalPeriod>39079</rotationalPeriod>
                <atmosphereDensity>14</atmosphereDensity>
                <generateCraters>true</generateCraters>
                <generateVolcanos>false</generateVolcanos>
                <generateStructures>false</generateStructures>
                <generateGeodes>false</generateGeodes>
                <craterFrequencyMultiplier>1.0</craterFrequencyMultiplier>
                <biomeIds>advancedrocketry:moon,advancedrocketry:moondark</biomeIds>
            </planet>
            <planet DIMID="177" name="Sol-175: 1">
                <isKnown>false</isKnown>
                <fogColor>1.0,1.0,1.0</fogColor>
                <skyColor>0.8,0.7194652,1.0</skyColor>
                <gravitationalMultiplier>47</gravitationalMultiplier>
                <orbitalDistance>190</orbitalDistance>
                <orbitalTheta>81</orbitalTheta>
                <orbitalPhi>-334</orbitalPhi>
                <avgTemperature>194</avgTemperature>
                <rotationalPeriod>231162</rotationalPeriod>
                <atmosphereDensity>27</atmosphereDensity>
                <generateCraters>true</generateCraters>
                <generateVolcanos>false</generateVolcanos>
                <generateStructures>false</generateStructures>
                <generateGeodes>false</generateGeodes>
                <craterFrequencyMultiplier>1.0</craterFrequencyMultiplier>
                <biomeIds>minecraft:mushroom_island_shore,traverse:green_swamp,minecraft:mutated_mesa_clear_rock,minecraft:savanna,minecraft:forest</biomeIds>
            </planet>
            <planet DIMID="178" name="Sol-175: 2">
                <isKnown>false</isKnown>
                <fogColor>1.0,1.0,1.0</fogColor>
                <skyColor>0.8,0.8275626,0.9647331</skyColor>
                <gravitationalMultiplier>67</gravitationalMultiplier>
                <orbitalDistance>167</orbitalDistance>
                <orbitalTheta>348</orbitalTheta>
                <orbitalPhi>-262</orbitalPhi>
                <avgTemperature>207</avgTemperature>
                <rotationalPeriod>79797</rotationalPeriod>
                <atmosphereDensity>14</atmosphereDensity>
                <generateCraters>true</generateCraters>
                <generateVolcanos>false</generateVolcanos>
                <generateStructures>false</generateStructures>
                <generateGeodes>false</generateGeodes>
                <craterFrequencyMultiplier>1.0</craterFrequencyMultiplier>
                <biomeIds>advancedrocketry:moon,advancedrocketry:moondark</biomeIds>
            </planet>
        </planet>
    </star>
    <star blackHole="true" name="Xoal" numGasGiants="0" numPlanets="0" size="2.5" temp="150" x="0" y="-19">
        <planet DIMID="193" name="Sol-193">
            <isKnown>false</isKnown>
            <GasGiant>true</GasGiant>
            <gas>oxygen</gas>
            <gas>nitrogen</gas>
            <gas>hydrogen</gas>
            <fogColor>1.0,1.0,1.0</fogColor>
            <skyColor>1.0,1.0,1.0</skyColor>
            <gravitationalMultiplier>115</gravitationalMultiplier>
            <orbitalDistance>257</orbitalDistance>
            <orbitalTheta>0</orbitalTheta>
            <orbitalPhi>0</orbitalPhi>
            <avgTemperature>425</avgTemperature>
            <rotationalPeriod>24000</rotationalPeriod>
            <atmosphereDensity>100</atmosphereDensity>
            <generateCraters>false</generateCraters>
            <generateVolcanos>false</generateVolcanos>
            <generateStructures>false</generateStructures>
            <generateGeodes>false</generateGeodes>
            <planet DIMID="194" name="Sol-193: 0">
                <isKnown>false</isKnown>
                <fogColor>1.0,1.0,1.0</fogColor>
                <skyColor>0.8,0.75943685,0.22497779</skyColor>
                <gravitationalMultiplier>78</gravitationalMultiplier>
                <orbitalDistance>188</orbitalDistance>
                <orbitalTheta>160</orbitalTheta>
                <orbitalPhi>-159</orbitalPhi>
                <avgTemperature>442</avgTemperature>
                <rotationalPeriod>50574</rotationalPeriod>
                <atmosphereDensity>27</atmosphereDensity>
                <generateCraters>true</generateCraters>
                <generateVolcanos>false</generateVolcanos>
                <generateStructures>false</generateStructures>
                <generateGeodes>false</generateGeodes>
                <craterFrequencyMultiplier>1.0</craterFrequencyMultiplier>
                <biomeIds>minecraft:mutated_mesa_clear_rock,minecraft:desert_hills,advancedrocketry:volcanicbarren,traverse:red_desert,traverse:badlands</biomeIds>
            </planet>
            <planet DIMID="195" name="Sol-193: 1">
                <isKnown>false</isKnown>
                <fogColor>1.0,1.0,1.0</fogColor>
                <skyColor>0.8,0.614345,0.0972234</skyColor>
                <gravitationalMultiplier>39</gravitationalMultiplier>
                <orbitalDistance>176</orbitalDistance>
                <orbitalTheta>344</orbitalTheta>
                <orbitalPhi>-211</orbitalPhi>
                <avgTemperature>457</avgTemperature>
                <rotationalPeriod>404592</rotationalPeriod>
                <atmosphereDensity>25</atmosphereDensity>
                <generateCraters>true</generateCraters>
                <generateVolcanos>true</generateVolcanos>
                <generateStructures>false</generateStructures>
                <generateGeodes>false</generateGeodes>
                <craterFrequencyMultiplier>1.0</craterFrequencyMultiplier>
                <volcanoFrequencyMultiplier>1.0</volcanoFrequencyMultiplier>
                <biomeIds>advancedrocketry:moon,advancedrocketry:moondark</biomeIds>
                <oceanBlock>minecraft:lava</oceanBlock>
            </planet>
            <planet DIMID="196" name="Sol-193: 2">
                <isKnown>false</isKnown>
                <fogColor>1.0,1.0,1.0</fogColor>
                <skyColor>0.8,0.9945369,0.0</skyColor>
                <gravitationalMultiplier>58</gravitationalMultiplier>
                <orbitalDistance>124</orbitalDistance>
                <orbitalTheta>9</orbitalTheta>
                <orbitalPhi>-209</orbitalPhi>
                <avgTemperature>544</avgTemperature>
                <rotationalPeriod>116857</rotationalPeriod>
                <atmosphereDensity>36</atmosphereDensity>
                <generateCraters>true</generateCraters>
                <generateVolcanos>true</generateVolcanos>
                <generateStructures>false</generateStructures>
                <generateGeodes>false</generateGeodes>
                <craterFrequencyMultiplier>1.0</craterFrequencyMultiplier>
                <volcanoFrequencyMultiplier>1.0</volcanoFrequencyMultiplier>
                <biomeIds>advancedrocketry:hotdryrock,advancedrocketry:volcanic,advancedrocketry:volcanicbarren</biomeIds>
                <oceanBlock>minecraft:lava</oceanBlock>
            </planet>
        </planet>
        <planet DIMID="197" name="Sol-197">
            <isKnown>false</isKnown>
            <GasGiant>true</GasGiant>
            <gas>oxygen</gas>
            <gas>nitrogen</gas>
            <gas>hydrogen</gas>
            <fogColor>1.0,1.0,1.0</fogColor>
            <skyColor>1.0,1.0,1.0</skyColor>
            <gravitationalMultiplier>114</gravitationalMultiplier>
            <orbitalDistance>221</orbitalDistance>
            <orbitalTheta>0</orbitalTheta>
            <orbitalPhi>0</orbitalPhi>
            <avgTemperature>459</avgTemperature>
            <rotationalPeriod>24000</rotationalPeriod>
            <atmosphereDensity>144</atmosphereDensity>
            <generateCraters>false</generateCraters>
            <generateVolcanos>false</generateVolcanos>
            <generateStructures>false</generateStructures>
            <generateGeodes>false</generateGeodes>
        </planet>
        <planet DIMID="198" name="Sol-198">
            <isKnown>false</isKnown>
            <GasGiant>true</GasGiant>
            <gas>oxygen</gas>
            <gas>nitrogen</gas>
            <gas>hydrogen</gas>
            <fogColor>1.0,1.0,1.0</fogColor>
            <skyColor>1.0,1.0,1.0</skyColor>
            <gravitationalMultiplier>89</gravitationalMultiplier>
            <orbitalDistance>246</orbitalDistance>
            <orbitalTheta>0</orbitalTheta>
            <orbitalPhi>0</orbitalPhi>
            <avgTemperature>435</avgTemperature>
            <rotationalPeriod>24000</rotationalPeriod>
            <atmosphereDensity>116</atmosphereDensity>
            <generateCraters>false</generateCraters>
            <generateVolcanos>false</generateVolcanos>
            <generateStructures>false</generateStructures>
            <generateGeodes>false</generateGeodes>
        </planet>
        <planet DIMID="199" name="Sol-199">
            <isKnown>false</isKnown>
            <GasGiant>true</GasGiant>
            <gas>oxygen</gas>
            <gas>nitrogen</gas>
            <gas>hydrogen</gas>
            <fogColor>1.0,1.0,1.0</fogColor>
            <skyColor>1.0,1.0,1.0</skyColor>
            <gravitationalMultiplier>93</gravitationalMultiplier>
            <orbitalDistance>218</orbitalDistance>
            <orbitalTheta>0</orbitalTheta>
            <orbitalPhi>0</orbitalPhi>
            <avgTemperature>462</avgTemperature>
            <rotationalPeriod>24000</rotationalPeriod>
            <atmosphereDensity>195</atmosphereDensity>
            <generateCraters>false</generateCraters>
            <generateVolcanos>false</generateVolcanos>
            <generateStructures>false</generateStructures>
            <generateGeodes>false</generateGeodes>
        </planet>
        <planet DIMID="200" name="Sol-200">
            <isKnown>false</isKnown>
            <GasGiant>true</GasGiant>
            <gas>oxygen</gas>
            <gas>nitrogen</gas>
            <gas>hydrogen</gas>
            <fogColor>1.0,1.0,1.0</fogColor>
            <skyColor>1.0,1.0,1.0</skyColor>
            <gravitationalMultiplier>116</gravitationalMultiplier>
            <orbitalDistance>277</orbitalDistance>
            <orbitalTheta>0</orbitalTheta>
            <orbitalPhi>0</orbitalPhi>
            <avgTemperature>410</avgTemperature>
            <rotationalPeriod>24000</rotationalPeriod>
            <atmosphereDensity>175</atmosphereDensity>
            <generateCraters>false</generateCraters>
            <generateVolcanos>false</generateVolcanos>
            <generateStructures>false</generateStructures>
            <generateGeodes>false</generateGeodes>
            <planet DIMID="201" name="Sol-200: 0">
                <isKnown>false</isKnown>
                <fogColor>1.0,1.0,1.0</fogColor>
                <skyColor>0.8,0.7777755,0.0</skyColor>
                <gravitationalMultiplier>68</gravitationalMultiplier>
                <orbitalDistance>104</orbitalDistance>
                <orbitalTheta>1</orbitalTheta>
                <orbitalPhi>-70</orbitalPhi>
                <avgTemperature>594</avgTemperature>
                <rotationalPeriod>76328</rotationalPeriod>
                <atmosphereDensity>26</atmosphereDensity>
                <generateCraters>true</generateCraters>
                <generateVolcanos>true</generateVolcanos>
                <generateStructures>false</generateStructures>
                <generateGeodes>false</generateGeodes>
                <craterFrequencyMultiplier>1.0</craterFrequencyMultiplier>
                <volcanoFrequencyMultiplier>1.0</volcanoFrequencyMultiplier>
                <biomeIds>advancedrocketry:hotdryrock,advancedrocketry:volcanic,advancedrocketry:volcanicbarren</biomeIds>
                <oceanBlock>minecraft:lava</oceanBlock>
            </planet>
        </planet>
        <planet DIMID="204" name="Sol-204">
            <isKnown>false</isKnown>
            <GasGiant>true</GasGiant>
            <gas>oxygen</gas>
            <gas>hydrogen</gas>
            <gas>nitrogen</gas>
            <fogColor>1.0,1.0,1.0</fogColor>
            <skyColor>1.0,1.0,1.0</skyColor>
            <gravitationalMultiplier>130</gravitationalMultiplier>
            <orbitalDistance>279</orbitalDistance>
            <orbitalTheta>0</orbitalTheta>
            <orbitalPhi>0</orbitalPhi>
            <avgTemperature>408</avgTemperature>
            <rotationalPeriod>24000</rotationalPeriod>
            <atmosphereDensity>108</atmosphereDensity>
            <generateCraters>false</generateCraters>
            <generateVolcanos>false</generateVolcanos>
            <generateStructures>false</generateStructures>
            <generateGeodes>false</generateGeodes>
        </planet>
        <planet DIMID="205" name="Sol-205">
            <isKnown>false</isKnown>
            <GasGiant>true</GasGiant>
            <gas>oxygen</gas>
            <gas>hydrogen</gas>
            <gas>nitrogen</gas>
            <fogColor>1.0,1.0,1.0</fogColor>
            <skyColor>1.0,1.0,1.0</skyColor>
            <gravitationalMultiplier>130</gravitationalMultiplier>
            <orbitalDistance>200</orbitalDistance>
            <orbitalTheta>0</orbitalTheta>
            <orbitalPhi>0</orbitalPhi>
            <avgTemperature>482</avgTemperature>
            <rotationalPeriod>24000</rotationalPeriod>
            <atmosphereDensity>139</atmosphereDensity>
            <generateCraters>false</generateCraters>
            <generateVolcanos>false</generateVolcanos>
            <generateStructures>false</generateStructures>
            <generateGeodes>false</generateGeodes>
            <planet DIMID="0" dimMapping="" name="Earth">
                <isKnown>true</isKnown>
                <fogColor>1.0,1.0,1.0</fogColor>
                <skyColor>1.0,1.0,1.0</skyColor>
                <gravitationalMultiplier>100</gravitationalMultiplier>
                <orbitalDistance>100</orbitalDistance>
                <orbitalTheta>0</orbitalTheta>
                <orbitalPhi>0</orbitalPhi>
                <avgTemperature>287</avgTemperature>
                <rotationalPeriod>24000</rotationalPeriod>
                <atmosphereDensity>100</atmosphereDensity>
                <generateCraters>false</generateCraters>
                <generateVolcanos>false</generateVolcanos>
                <generateStructures>false</generateStructures>
                <generateGeodes>false</generateGeodes>
            </planet>
            <planet DIMID="0" dimMapping="" name="Earth">
                <isKnown>true</isKnown>
                <fogColor>1.0,1.0,1.0</fogColor>
                <skyColor>1.0,1.0,1.0</skyColor>
                <gravitationalMultiplier>100</gravitationalMultiplier>
                <orbitalDistance>100</orbitalDistance>
                <orbitalTheta>0</orbitalTheta>
                <orbitalPhi>0</orbitalPhi>
                <avgTemperature>287</avgTemperature>
                <rotationalPeriod>24000</rotationalPeriod>
                <atmosphereDensity>100</atmosphereDensity>
                <generateCraters>false</generateCraters>
                <generateVolcanos>false</generateVolcanos>
                <generateStructures>false</generateStructures>
                <generateGeodes>false</generateGeodes>
            </planet>
            <planet DIMID="0" dimMapping="" name="Earth">
                <isKnown>true</isKnown>
                <fogColor>1.0,1.0,1.0</fogColor>
                <skyColor>1.0,1.0,1.0</skyColor>
                <gravitationalMultiplier>100</gravitationalMultiplier>
                <orbitalDistance>100</orbitalDistance>
                <orbitalTheta>0</orbitalTheta>
                <orbitalPhi>0</orbitalPhi>
                <avgTemperature>287</avgTemperature>
                <rotationalPeriod>24000</rotationalPeriod>
                <atmosphereDensity>100</atmosphereDensity>
                <generateCraters>false</generateCraters>
                <generateVolcanos>false</generateVolcanos>
                <generateStructures>false</generateStructures>
                <generateGeodes>false</generateGeodes>
            </planet>
            <planet DIMID="0" dimMapping="" name="Earth">
                <isKnown>true</isKnown>
                <fogColor>1.0,1.0,1.0</fogColor>
                <skyColor>1.0,1.0,1.0</skyColor>
                <gravitationalMultiplier>100</gravitationalMultiplier>
                <orbitalDistance>100</orbitalDistance>
                <orbitalTheta>0</orbitalTheta>
                <orbitalPhi>0</orbitalPhi>
                <avgTemperature>287</avgTemperature>
                <rotationalPeriod>24000</rotationalPeriod>
                <atmosphereDensity>100</atmosphereDensity>
                <generateCraters>false</generateCraters>
                <generateVolcanos>false</generateVolcanos>
                <generateStructures>false</generateStructures>
                <generateGeodes>false</generateGeodes>
            </planet>
            <planet DIMID="0" dimMapping="" name="Earth">
                <isKnown>true</isKnown>
                <fogColor>1.0,1.0,1.0</fogColor>
                <skyColor>1.0,1.0,1.0</skyColor>
                <gravitationalMultiplier>100</gravitationalMultiplier>
                <orbitalDistance>100</orbitalDistance>
                <orbitalTheta>0</orbitalTheta>
                <orbitalPhi>0</orbitalPhi>
                <avgTemperature>287</avgTemperature>
                <rotationalPeriod>24000</rotationalPeriod>
                <atmosphereDensity>100</atmosphereDensity>
                <generateCraters>false</generateCraters>
                <generateVolcanos>false</generateVolcanos>
                <generateStructures>false</generateStructures>
                <generateGeodes>false</generateGeodes>
            </planet>
        </planet>
        <planet DIMID="211" name="Sol-211">
            <isKnown>false</isKnown>
            <GasGiant>true</GasGiant>
            <gas>oxygen</gas>
            <gas>hydrogen</gas>
            <gas>nitrogen</gas>
            <fogColor>1.0,1.0,1.0</fogColor>
            <skyColor>1.0,1.0,1.0</skyColor>
            <gravitationalMultiplier>130</gravitationalMultiplier>
            <orbitalDistance>182</orbitalDistance>
            <orbitalTheta>0</orbitalTheta>
            <orbitalPhi>0</orbitalPhi>
            <avgTemperature>505</avgTemperature>
            <rotationalPeriod>24000</rotationalPeriod>
            <atmosphereDensity>195</atmosphereDensity>
            <generateCraters>false</generateCraters>
            <generateVolcanos>false</generateVolcanos>
            <generateStructures>false</generateStructures>
            <generateGeodes>false</generateGeodes>
            <planet DIMID="0" dimMapping="" name="Earth">
                <isKnown>true</isKnown>
                <fogColor>1.0,1.0,1.0</fogColor>
                <skyColor>1.0,1.0,1.0</skyColor>
                <gravitationalMultiplier>100</gravitationalMultiplier>
                <orbitalDistance>100</orbitalDistance>
                <orbitalTheta>0</orbitalTheta>
                <orbitalPhi>0</orbitalPhi>
                <avgTemperature>287</avgTemperature>
                <rotationalPeriod>24000</rotationalPeriod>
                <atmosphereDensity>100</atmosphereDensity>
                <generateCraters>false</generateCraters>
                <generateVolcanos>false</generateVolcanos>
                <generateStructures>false</generateStructures>
                <generateGeodes>false</generateGeodes>
            </planet>
            <planet DIMID="0" dimMapping="" name="Earth">
                <isKnown>true</isKnown>
                <fogColor>1.0,1.0,1.0</fogColor>
                <skyColor>1.0,1.0,1.0</skyColor>
                <gravitationalMultiplier>100</gravitationalMultiplier>
                <orbitalDistance>100</orbitalDistance>
                <orbitalTheta>0</orbitalTheta>
                <orbitalPhi>0</orbitalPhi>
                <avgTemperature>287</avgTemperature>
                <rotationalPeriod>24000</rotationalPeriod>
                <atmosphereDensity>100</atmosphereDensity>
                <generateCraters>false</generateCraters>
                <generateVolcanos>false</generateVolcanos>
                <generateStructures>false</generateStructures>
                <generateGeodes>false</generateGeodes>
            </planet>
        </planet>
        <planet DIMID="147" name="Aurellia">
            <isKnown>true</isKnown>
            <fogColor>1.0,1.0,1.0</fogColor>
            <skyColor>1.0,1.0,1.0</skyColor>
            <gravitationalMultiplier>200</gravitationalMultiplier>
            <orbitalDistance>30</orbitalDistance>
            <orbitalTheta>0</orbitalTheta>
            <orbitalPhi>30</orbitalPhi>
            <avgTemperature>1107</avgTemperature>
            <rotationalPeriod>2400</rotationalPeriod>
            <atmosphereDensity>80</atmosphereDensity>
            <generateCraters>false</generateCraters>
            <generateVolcanos>false</generateVolcanos>
            <generateStructures>false</generateStructures>
            <generateGeodes>false</generateGeodes>
            <biomeIds>advancedrocketry:hotdryrock,advancedrocketry:crystalchasms,minecraft:ocean</biomeIds>
            <oceanBlock>tconstruct:molten_obsidian</oceanBlock>
        </planet>
        <planet DIMID="183" name="Sol-183">
            <isKnown>false</isKnown>
            <GasGiant>true</GasGiant>
            <gas>oxygen</gas>
            <gas>nitrogen</gas>
            <gas>hydrogen</gas>
            <fogColor>1.0,1.0,1.0</fogColor>
            <skyColor>1.0,1.0,1.0</skyColor>
            <gravitationalMultiplier>103</gravitationalMultiplier>
            <orbitalDistance>203</orbitalDistance>
            <orbitalTheta>0</orbitalTheta>
            <orbitalPhi>0</orbitalPhi>
            <avgTemperature>479</avgTemperature>
            <rotationalPeriod>24000</rotationalPeriod>
            <atmosphereDensity>180</atmosphereDensity>
            <generateCraters>false</generateCraters>
            <generateVolcanos>false</generateVolcanos>
            <generateStructures>false</generateStructures>
            <generateGeodes>false</generateGeodes>
            <planet DIMID="184" name="Sol-183: 0">
                <isKnown>false</isKnown>
                <hasRings>true</hasRings>
                <ringColor>0.8,0.895851,0.0</ringColor>
                <fogColor>1.0,1.0,1.0</fogColor>
                <skyColor>0.8,0.895851,0.0</skyColor>
                <gravitationalMultiplier>38</gravitationalMultiplier>
                <orbitalDistance>127</orbitalDistance>
                <orbitalTheta>42</orbitalTheta>
                <orbitalPhi>-251</orbitalPhi>
                <avgTemperature>538</avgTemperature>
                <rotationalPeriod>437381</rotationalPeriod>
                <atmosphereDensity>30</atmosphereDensity>
                <generateCraters>true</generateCraters>
                <generateVolcanos>true</generateVolcanos>
                <generateStructures>false</generateStructures>
                <generateGeodes>false</generateGeodes>
                <craterFrequencyMultiplier>1.0</craterFrequencyMultiplier>
                <volcanoFrequencyMultiplier>1.0</volcanoFrequencyMultiplier>
                <biomeIds>advancedrocketry:hotdryrock,advancedrocketry:volcanic,advancedrocketry:volcanicbarren</biomeIds>
                <oceanBlock>minecraft:lava</oceanBlock>
            </planet>
            <planet DIMID="185" name="Sol-183: 1">
                <isKnown>false</isKnown>
                <fogColor>1.0,1.0,1.0</fogColor>
                <skyColor>0.8,0.5771184,0.08679789</skyColor>
                <gravitationalMultiplier>61</gravitationalMultiplier>
                <orbitalDistance>177</orbitalDistance>
                <orbitalTheta>308</orbitalTheta>
                <orbitalPhi>354</orbitalPhi>
                <avgTemperature>456</avgTemperature>
                <rotationalPeriod>105735</rotationalPeriod>
                <atmosphereDensity>18</atmosphereDensity>
                <generateCraters>true</generateCraters>
                <generateVolcanos>true</generateVolcanos>
                <generateStructures>false</generateStructures>
                <generateGeodes>false</generateGeodes>
                <craterFrequencyMultiplier>1.0</craterFrequencyMultiplier>
                <volcanoFrequencyMultiplier>1.0</volcanoFrequencyMultiplier>
                <seaLevel>44</seaLevel>
                <biomeIds>advancedrocketry:moon,advancedrocketry:moondark</biomeIds>
                <oceanBlock>minecraft:lava</oceanBlock>
            </planet>
            <planet DIMID="186" name="Sol-183: 2">
                <isKnown>false</isKnown>
                <fogColor>1.0,1.0,1.0</fogColor>
                <skyColor>0.8,0.9683665,0.0</skyColor>
                <gravitationalMultiplier>75</gravitationalMultiplier>
                <orbitalDistance>138</orbitalDistance>
                <orbitalTheta>340</orbitalTheta>
                <orbitalPhi>-52</orbitalPhi>
                <avgTemperature>516</avgTemperature>
                <rotationalPeriod>56888</rotationalPeriod>
                <atmosphereDensity>14</atmosphereDensity>
                <generateCraters>true</generateCraters>
                <generateVolcanos>true</generateVolcanos>
                <generateStructures>false</generateStructures>
                <generateGeodes>false</generateGeodes>
                <craterFrequencyMultiplier>1.0</craterFrequencyMultiplier>
                <volcanoFrequencyMultiplier>1.0</volcanoFrequencyMultiplier>
                <biomeIds>advancedrocketry:moon,advancedrocketry:moondark</biomeIds>
                <oceanBlock>minecraft:lava</oceanBlock>
            </planet>
        </planet>
        <planet DIMID="187" name="Sol-187">
            <isKnown>false</isKnown>
            <GasGiant>true</GasGiant>
            <gas>oxygen</gas>
            <gas>nitrogen</gas>
            <gas>hydrogen</gas>
            <fogColor>1.0,1.0,1.0</fogColor>
            <skyColor>1.0,1.0,1.0</skyColor>
            <gravitationalMultiplier>130</gravitationalMultiplier>
            <orbitalDistance>239</orbitalDistance>
            <orbitalTheta>0</orbitalTheta>
            <orbitalPhi>0</orbitalPhi>
            <avgTemperature>441</avgTemperature>
            <rotationalPeriod>24000</rotationalPeriod>
            <atmosphereDensity>112</atmosphereDensity>
            <generateCraters>false</generateCraters>
            <generateVolcanos>false</generateVolcanos>
            <generateStructures>false</generateStructures>
            <generateGeodes>false</generateGeodes>
            <planet DIMID="192" name="Sol-187: 4">
                <isKnown>false</isKnown>
                <fogColor>1.0,1.0,1.0</fogColor>
                <skyColor>0.8,0.5382596,0.0</skyColor>
                <gravitationalMultiplier>77</gravitationalMultiplier>
                <orbitalDistance>133</orbitalDistance>
                <orbitalTheta>353</orbitalTheta>
                <orbitalPhi>25</orbitalPhi>
                <avgTemperature>526</avgTemperature>
                <rotationalPeriod>52570</rotationalPeriod>
                <atmosphereDensity>25</atmosphereDensity>
                <generateCraters>true</generateCraters>
                <generateVolcanos>true</generateVolcanos>
                <generateStructures>false</generateStructures>
                <generateGeodes>false</generateGeodes>
                <craterFrequencyMultiplier>1.0</craterFrequencyMultiplier>
                <volcanoFrequencyMultiplier>1.0</volcanoFrequencyMultiplier>
                <biomeIds>advancedrocketry:moon,advancedrocketry:moondark</biomeIds>
                <oceanBlock>minecraft:lava</oceanBlock>
            </planet>
            <planet DIMID="188" name="Sol-187: 0">
                <isKnown>false</isKnown>
                <fogColor>1.0,1.0,1.0</fogColor>
                <skyColor>0.8,0.9845816,0.0</skyColor>
                <gravitationalMultiplier>49</gravitationalMultiplier>
                <orbitalDistance>131</orbitalDistance>
                <orbitalTheta>206</orbitalTheta>
                <orbitalPhi>-174</orbitalPhi>
                <avgTemperature>530</avgTemperature>
                <rotationalPeriod>203996</rotationalPeriod>
                <atmosphereDensity>17</atmosphereDensity>
                <generateCraters>true</generateCraters>
                <generateVolcanos>true</generateVolcanos>
                <generateStructures>false</generateStructures>
                <generateGeodes>false</generateGeodes>
                <craterFrequencyMultiplier>1.0</craterFrequencyMultiplier>
                <volcanoFrequencyMultiplier>1.0</volcanoFrequencyMultiplier>
                <seaLevel>72</seaLevel>
                <biomeIds>advancedrocketry:moon,advancedrocketry:moondark</biomeIds>
                <oceanBlock>minecraft:lava</oceanBlock>
            </planet>
            <planet DIMID="189" name="Sol-187: 1">
                <isKnown>false</isKnown>
                <fogColor>1.0,1.0,1.0</fogColor>
                <skyColor>0.8,0.50748396,0.25215685</skyColor>
                <gravitationalMultiplier>76</gravitationalMultiplier>
                <orbitalDistance>202</orbitalDistance>
                <orbitalTheta>180</orbitalTheta>
                <orbitalPhi>-217</orbitalPhi>
                <avgTemperature>426</avgTemperature>
                <rotationalPeriod>54672</rotationalPeriod>
                <atmosphereDensity>32</atmosphereDensity>
                <generateCraters>true</generateCraters>
                <generateVolcanos>false</generateVolcanos>
                <generateStructures>false</generateStructures>
                <generateGeodes>false</generateGeodes>
                <craterFrequencyMultiplier>1.0</craterFrequencyMultiplier>
                <biomeIds>advancedrocketry:stormland,minecraft:mutated_savanna,traverse:mountainous_desert,minecraft:savanna_rock,minecraft:frozen_ocean</biomeIds>
            </planet>
            <planet DIMID="190" name="Sol-187: 2">
                <isKnown>false</isKnown>
                <fogColor>1.0,1.0,1.0</fogColor>
                <skyColor>0.8,0.6796143,0.0</skyColor>
                <gravitationalMultiplier>61</gravitationalMultiplier>
                <orbitalDistance>143</orbitalDistance>
                <orbitalTheta>39</orbitalTheta>
                <orbitalPhi>35</orbitalPhi>
                <avgTemperature>507</avgTemperature>
                <rotationalPeriod>105735</rotationalPeriod>
                <atmosphereDensity>14</atmosphereDensity>
                <generateCraters>true</generateCraters>
                <generateVolcanos>true</generateVolcanos>
                <generateStructures>false</generateStructures>
                <generateGeodes>false</generateGeodes>
                <craterFrequencyMultiplier>1.0</craterFrequencyMultiplier>
                <volcanoFrequencyMultiplier>1.0</volcanoFrequencyMultiplier>
                <seaLevel>72</seaLevel>
                <biomeIds>advancedrocketry:moon,advancedrocketry:moondark</biomeIds>
                <oceanBlock>minecraft:lava</oceanBlock>
            </planet>
            <planet DIMID="191" name="Sol-187: 3">
                <isKnown>false</isKnown>
                <fogColor>1.0,1.0,1.0</fogColor>
                <skyColor>0.8,0.8416947,0.080251634</skyColor>
                <gravitationalMultiplier>78</gravitationalMultiplier>
                <orbitalDistance>170</orbitalDistance>
                <orbitalTheta>325</orbitalTheta>
                <orbitalPhi>-85</orbitalPhi>
                <avgTemperature>465</avgTemperature>
                <rotationalPeriod>50574</rotationalPeriod>
                <atmosphereDensity>17</atmosphereDensity>
                <generateCraters>true</generateCraters>
                <generateVolcanos>true</generateVolcanos>
                <generateStructures>false</generateStructures>
                <generateGeodes>false</generateGeodes>
                <craterFrequencyMultiplier>1.0</craterFrequencyMultiplier>
                <volcanoFrequencyMultiplier>1.0</volcanoFrequencyMultiplier>
                <biomeIds>advancedrocketry:moon,advancedrocketry:moondark</biomeIds>
                <oceanBlock>minecraft:lava</oceanBlock>
            </planet>
        </planet>
    </star>
</galaxy>
